AUTHORS.rst
CONTRIBUTING.rst
HISTORY.rst
LICENSE
MANIFEST.in
README.rst
setup.cfg
setup.py
docs/Makefile
docs/authors.rst
docs/conf.py
docs/contributing.rst
docs/history.rst
docs/index.rst
docs/installation.rst
docs/make.bat
docs/readme.rst
docs/usage.rst
hyperscreen/__init__.py
hyperscreen/cli.py
hyperscreen/hyperscreen.py
hyperscreen.egg-info/PKG-INFO
hyperscreen.egg-info/SOURCES.txt
hyperscreen.egg-info/dependency_links.txt
hyperscreen.egg-info/entry_points.txt
hyperscreen.egg-info/not-zip-safe
hyperscreen.egg-info/top_level.txt
tests/__init__.py
tests/test_hyperscreen.py